torch_treecrf/__init__.py
torch_treecrf-0.2.0.dist-info/COPYING
torch_treecrf-0.2.0.dist-info/METADATA
torch_treecrf-0.2.0.dist-info/WHEEL
torch_treecrf-0.2.0.dist-info/top_level.txt
torch_treecrf-0.2.0.dist-info/zip-safe
torch_treecrf-0.2.0.dist-info/RECORD
