Metadata-Version: 2.1
Name: torch-treecrf
Version: 0.2.0
Summary: A PyTorch implementation of Tree-structured Conditional Random Fields.
Home-page: https://github.com/althonos/torch-treecrf
Author: Martin Larralde
Author-email: martin.larralde@embl.de
License: MIT
Project-URL: Bug Tracker, https://github.com/althonos/torch-treecrf/issues
Project-URL: Changelog, https://github.com/althonos/torch-treecrf/blob/master/CHANGELOG.md
Project-URL: Coverage, https://codecov.io/gh/althonos/torch-treecrf/
Project-URL: Builds, https://github.com/althonos/torch-treecrf/actions
Project-URL: PyPI, https://pypi.org/project/torch-treecrf
Keywords: torch
Platform: any
Classifier: Development Status :: 3 - Alpha
Classifier: Intended Audience :: Developers
Classifier: Intended Audience :: Science/Research
Classifier: License :: OSI Approved :: MIT License
Classifier: Programming Language :: Python :: 3
Classifier: Topic :: Scientific/Engineering :: Artificial Intelligence
Classifier: Topic :: Scientific/Engineering :: Mathematics
Classifier: Topic :: Software Development :: Libraries :: Python Modules
Classifier: Typing :: Typed
Requires-Python: >=3.6
License-File: COPYING
Requires-Dist: torch ~=2.0
